{"_type":"export","__export_format":4,"__export_date":"2023-10-09T13:28:32.206Z","__export_source":"insomnia.desktop.app:v8.2.0","resources":[{"_id":"req_3f141f9b89184aeb942d60caf5e4814b","parentId":"wrk_scratchpad","modified":1696566122192,"created":1696566082712,"url":"localhost:8080/api/products/1","name":"/api/products/{id}","description":"","method":"GET","body":{},"parameters":[],"headers":[{"name":"User-Agent","value":"insomnia/8.1.0"}],"authentication":{},"metaSortKey":-1696566082712,"isPrivate":false,"settingStoreCookies":true,"settingSendCookies":true,"settingDisableRenderRequestBody":false,"settingEncodeUrl":true,"settingRebuildPath":true,"settingFollowRedirects":"global","_type":"request"},{"_id":"wrk_scratchpad","parentId":null,"modified":1696056702009,"created":1696056702009,"name":"Scratch Pad","description":"","scope":"collection","_type":"workspace"},{"_id":"req_267de2a6b80d4b13b03cacd2e1b4d3b5","parentId":"wrk_scratchpad","modified":1696566076589,"created":1696565657707,"url":"localhost:8080/api/products","name":"/api/products","description":"","method":"POST","body":{"mimeType":"application/json","text":"{\n     \"name\" : \"iphone\",\n     \"category\" : \"MobilePhone\",\n     \"price\" : 50000,\n     \"description\" : \"Iphone 15 plus\",\n     \"manufacturer\" : \"Apple\",\n     \"availableItems\" : 50,\n     \"imageUrl\" : \"test url\"\n}"},"parameters":[],"headers":[{"name":"Content-Type","value":"application/json"},{"name":"User-Agent","value":"insomnia/8.1.0"}],"authentication":{},"metaSortKey":-1696565657707,"isPrivate":false,"settingStoreCookies":true,"settingSendCookies":true,"settingDisableRenderRequestBody":false,"settingEncodeUrl":true,"settingRebuildPath":true,"settingFollowRedirects":"global","_type":"request"},{"_id":"req_2a4c2d8d65b240d8b99fed69c0ec1491","parentId":"wrk_scratchpad","modified":1696565652120,"created":1696082091244,"url":"localhost:8080/api/users","name":"/api/users","description":"","method":"POST","body":{"mimeType":"application/json","text":"{\n\t\"firstName\": \"arjun\",\n\t\"lastName\": \"alagesan\",\n\t\"email\": \"arjun@gmail.com\",\n\t\"password\": \"test\",\n\t\"contactNumber\": \"98363737\"\n}"},"parameters":[],"headers":[{"name":"Content-Type","value":"application/json"},{"name":"User-Agent","value":"insomnia/8.1.0"}],"authentication":{},"metaSortKey":-1696082091244,"isPrivate":false,"settingStoreCookies":true,"settingSendCookies":true,"settingDisableRenderRequestBody":false,"settingEncodeUrl":true,"settingRebuildPath":true,"settingFollowRedirects":"global","_type":"request"},{"_id":"req_019432c173bb41debe9fa7540c59d9cd","parentId":"wrk_scratchpad","modified":1696566461212,"created":1696566215581,"url":"localhost:8080/api/orders","name":"/api/orders/","description":"","method":"POST","body":{"mimeType":"application/json","text":"{\n\t\"userId\": 1,\n\t\"lineItems\" : [\n\t {\n\t\t \"productId\" : 1,\n\t\t \"quantity\" : 1\n\t }\n\t]\n}"},"parameters":[],"headers":[{"name":"Content-Type","value":"application/json"},{"name":"User-Agent","value":"insomnia/8.1.0"}],"authentication":{},"metaSortKey":-1696082091219,"isPrivate":false,"settingStoreCookies":true,"settingSendCookies":true,"settingDisableRenderRequestBody":false,"settingEncodeUrl":true,"settingRebuildPath":true,"settingFollowRedirects":"global","_type":"request"},{"_id":"req_611b6a107a7a4915bf44e04eb985822b","parentId":"wrk_scratchpad","modified":1696566552257,"created":1696566535645,"url":"localhost:8080/api/orders/1","name":"/api/orders/{id}","description":"","method":"GET","body":{},"parameters":[],"headers":[{"name":"User-Agent","value":"insomnia/8.1.0"}],"authentication":{},"metaSortKey":-1696082091206.5,"isPrivate":false,"settingStoreCookies":true,"settingSendCookies":true,"settingDisableRenderRequestBody":false,"settingEncodeUrl":true,"settingRebuildPath":true,"settingFollowRedirects":"global","_type":"request"},{"_id":"req_0785be266ef944a4ba11e651547be2e6","parentId":"wrk_scratchpad","modified":1696566559312,"created":1696566134923,"url":"localhost:8080/api/users/1","name":"/api/users/{id}","description":"","method":"GET","body":{},"parameters":[],"headers":[{"name":"User-Agent","value":"insomnia/8.1.0"}],"authentication":{},"metaSortKey":-1696082091194,"isPrivate":false,"settingStoreCookies":true,"settingSendCookies":true,"settingDisableRenderRequestBody":false,"settingEncodeUrl":true,"settingRebuildPath":true,"settingFollowRedirects":"global","_type":"request"},{"_id":"env_99d30891da4bdcebc63947a8fc17f076de878684","parentId":"wrk_scratchpad","modified":1696056702067,"created":1696056702067,"name":"Base Environment","data":{},"dataPropertyOrder":null,"color":null,"isPrivate":false,"metaSortKey":1696056702067,"_type":"environment"},{"_id":"jar_99d30891da4bdcebc63947a8fc17f076de878684","parentId":"wrk_scratchpad","modified":1696056702069,"created":1696056702069,"name":"Default Jar","cookies":[],"_type":"cookie_jar"}]}